mimchine/__init__.py
mimchine/__main__.py
mimchine/cli.py
mimchine/config.py
mimchine/containers.py
mimchine/integration.py
mimchine/util.py
mimchine-0.25.0.dist-info/METADATA
mimchine-0.25.0.dist-info/WHEEL
mimchine-0.25.0.dist-info/entry_points.txt
mimchine-0.25.0.dist-info/RECORD
