Metadata-Version: 2.3
Name: mimchine
Version: 0.25.0
Summary: well integrated mini machines with rootless podman
Author: redthing1
Author-email: redthing1@alt.icu
Requires-Python: >=3.9,<4.0
Classifier: Programming Language :: Python :: 3
Classifier: Programming Language :: Python :: 3.9
Classifier: Programming Language :: Python :: 3.10
Classifier: Programming Language :: Python :: 3.11
Classifier: Programming Language :: Python :: 3.12
Classifier: Programming Language :: Python :: 3.13
Requires-Dist: minlog (>=0.6.0,<0.7.0)
Requires-Dist: platformdirs (>=4.2.0,<5.0.0)
Requires-Dist: sh (>=2.2.2,<3.0.0)
Requires-Dist: single-source (>=0.4.0,<0.5.0)
Requires-Dist: tomli (>=2.0.1,<3.0.0) ; python_version < "3.11"
Requires-Dist: tomli-w (>=1.0.0,<2.0.0)
Requires-Dist: typer (>=0.15.2,<0.16.0)
